azaux/__init__.py
azaux/container_manager.py
azaux/queue_manager.py
azaux/storage_resource.py
azaux/table_manager.py
azaux-0.2.2.dist-info/LICENSE
azaux-0.2.2.dist-info/METADATA
azaux-0.2.2.dist-info/WHEEL
azaux-0.2.2.dist-info/RECORD
